infusevideo/__init__.py
infusevideo/auth.py
infusevideo/authserver.py
infusevideo/client.py
infusevideo/config.py
infusevideo/errors.py
infusevideo/filterwarnings.py
infusevideo/loghelpers.py
infusevideo/scope.py
infusevideo_sdk-0.3.0.dist-info/LICENSE
infusevideo_sdk-0.3.0.dist-info/METADATA
infusevideo_sdk-0.3.0.dist-info/WHEEL
infusevideo_sdk-0.3.0.dist-info/top_level.txt
infusevideo_sdk-0.3.0.dist-info/RECORD
