Metadata-Version: 2.1
Name: infusevideo-sdk
Version: 0.3.0
Summary: Python SDK for the Infuse Video API
Home-page: https://www.infuse.video
Author: Infuse Video
Author-email: support@infuse.video
License: MIT
Classifier: Development Status :: 3 - Alpha
Classifier: Intended Audience :: Developers
Classifier: License :: OSI Approved :: MIT License
Classifier: Operating System :: OS Independent
Classifier: Programming Language :: Python :: 3.9
Classifier: Programming Language :: Python :: 3.10
Classifier: Topic :: Multimedia :: Video
Classifier: Topic :: Software Development :: Libraries
Requires-Python: >=3.9
License-File: LICENSE
Requires-Dist: requests >=2.27.1
Requires-Dist: pydantic <2,>=1.9.0
